com_digitalruiz_simple_http_client/__init__.py
com_digitalruiz_simple_http_client/simple_http_client.py
com_digitalruiz_simple_http_client-0.0.4.dist-info/LICENSE
com_digitalruiz_simple_http_client-0.0.4.dist-info/METADATA
com_digitalruiz_simple_http_client-0.0.4.dist-info/WHEEL
com_digitalruiz_simple_http_client-0.0.4.dist-info/top_level.txt
com_digitalruiz_simple_http_client-0.0.4.dist-info/RECORD
