Metadata-Version: 2.2
Name: com_digitalruiz_simple_http_client
Version: 0.0.4
Summary: A small package to create and use an http client
Author-email: Reyes Ruiz <reyes@digitalruiz.com>
Project-URL: Homepage, https://github.com/reyesruiz/simple_http_client
Project-URL: Bug Tracker, https://github.com/reyesruiz/my_logger/simple_http_client
Classifier: Programming Language :: Python :: 3
Classifier: License :: OSI Approved :: MIT License
Classifier: Operating System :: OS Independent
Requires-Python: >=3.7
License-File: LICENSE
Requires-Dist: requests
Requires-Dist: com-digitalruiz-my-logger
